setup.py
pypercorn/__init__.py
pypercorn/utilities.py
pypercorn.egg-info/PKG-INFO
pypercorn.egg-info/SOURCES.txt
pypercorn.egg-info/dependency_links.txt
pypercorn.egg-info/requires.txt
pypercorn.egg-info/top_level.txt
pypercorn/algorithms/images/satellite.py
pypercorn/algorithms/images/segmentation.py